[{"callsign":"UAL1159","number":"UA1159","origin":null,"duration":{"hours":3,"minutes":45,"seconds":23},"day":"2021-01-31T00:00:00.000Z"},{"callsign":"UAL372","number":"UA372","origin":null,"duration":{"minutes":25,"seconds":19},"day":"2021-01-31T00:00:00.000Z"},{"callsign":"EJA157","number":"1I157","origin":"KSTL","duration":{"hours":3,"minutes":52,"seconds":9},"day":"2021-01-31T00:00:00.000Z"},{"callsign":"UAL1687","number":"UA1687","origin":"KPDX","duration":{"hours":1,"minutes":28,"seconds":26},"day":"2021-01-31T00:00:00.000Z"},{"callsign":"DAL311","number":"DL311","origin":"KJFK","duration":{"hours":6,"minutes":5,"seconds":56},"day":"2021-01-31T00:00:00.000Z"},{"callsign":"SKW5805","number":"OO5805","origin":null,"duration":{"hours":1,"minutes":43,"seconds":16},"day":"2021-01-31T00:00:00.000Z"},{"callsign":"UAL858","number":null,"origin":null,"duration":{"hours":9,"minutes":39,"seconds":38},"day":"2021-01-31T00:00:00.000Z"},{"callsign":"UAL306","number":"UA306","origin":"02XS","duration":{"hours":3,"minutes":36,"seconds":26},"day":"2021-01-31T00:00:00.000Z"},{"callsign":"SKW3329","number":"OO3329","origin":"KDAL","duration":{"hours":3,"minutes":58,"seconds":46},"day":"2021-01-31T00:00:00.000Z"},{"callsign":"SKW4792","number":"OO4792","origin":"KRDM","duration":{"hours":1,"minutes":24,"seconds":10},"day":"2021-01-31T00:00:00.000Z"}]