[{"callsign":"SKW3329","number":"OO3329","origin":"KDAL","duration":{"hours":3,"minutes":58,"seconds":46},"day":"2021-01-31T00:00:00.000Z"},{"callsign":"SKW4760","number":"OO4760","origin":"KONT","duration":{"minutes":56,"seconds":57},"day":"2021-01-31T00:00:00.000Z"},{"callsign":"UAL306","number":"UA306","origin":"02XS","duration":{"hours":3,"minutes":36,"seconds":26},"day":"2021-01-31T00:00:00.000Z"},{"callsign":"SKW5974","number":"OO5974","origin":null,"duration":{"hours":1,"minutes":47,"seconds":31},"day":"2021-01-31T00:00:00.000Z"},{"callsign":"UAL748","number":"UA748","origin":"KEWR","duration":{"hours":5,"minutes":40,"seconds":43},"day":"2021-01-31T00:00:00.000Z"},{"callsign":"SKW4789","number":"OO4789","origin":"KPSP","duration":{"hours":1,"minutes":11,"seconds":8},"day":"2021-01-31T00:00:00.000Z"},{"callsign":"AIC183","number":"AI183","origin":"VIDP","duration":{"hours":14,"minutes":46,"seconds":46},"day":"2021-01-31T00:00:00.000Z"},{"callsign":"UAL59","number":"UA59","origin":"EDDF","duration":{"hours":11,"minutes":8,"seconds":34},"day":"2021-01-31T00:00:00.000Z"},{"callsign":"EJA157","number":"1I157","origin":"KSTL","duration":{"hours":3,"minutes":52,"seconds":9},"day":"2021-01-31T00:00:00.000Z"},{"callsign":"ASA289","number":"AS289","origin":"KFLL","duration":{"hours":6,"minutes":1,"seconds":15},"day":"2021-01-31T00:00:00.000Z"}]